{
  "title": "\u7f8e\u4f0a\u6218\u4e89\u5b9e\u65f6\u5c40\u52bf\u6458\u8981",
  "description": "\u57fa\u4e8e CBS/AP/NYT/Independent \u7b49\u4e3b\u6d41\u5a92\u4f53\u7684\u5b9e\u65f6\u6218\u51b5\u66f4\u65b0",
  "updated": "2026-04-25T12:00:00+08:00",
  "files": [
    {
      "id": "2026-04-25T12",
      "file": "2026-04-25T12.md",
      "date": "2026-04-25T12:00:00+08:00",
      "title": {
        "zh": "\u7f8e\u4f0a\u548c\u8c08\u6301\u7eed\u63a8\u8fdb\uff0c\u4f0a\u6717\u5916\u957f\u62b5\u5df4\u8c08\u5224",
        "en": "US-Iran Peace Talks Intensify as Iranian Foreign Minister Arrives in Pakistan"
      },
      "tags": [
        "diplomacy",
        "military"
      ]
    },
    {
      "id": "2026-04-09T18",
      "file": "2026-04-09T18.md",
      "date": "2026-04-09T18:00:00+08:00",
      "title": {
        "zh": "\u505c\u706b\u534f\u8bae\u6301\u7eed\u7d27\u5f20\uff1a\u7279\u6717\u666e\u589e\u5175\u5a01\u80c1\u7ee7\u7eed\uff0c\u9ece\u5df4\u5ae9\u5c40\u52bf\u5347\u7ea7",
        "en": "\u505c\u706b\u534f\u8bae\u6301\u7eed\u7d27\u5f20\uff1a\u7279\u6717\u666e\u589e\u5175\u5a01\u80c1\u7ee7\u7eed\uff0c\u9ece\u5df4\u5ae9\u5c40\u52bf\u5347\u7ea7"
      },
      "tags": [
        ""
      ]
    },
    {
      "id": "2026-04-09T17",
      "file": "2026-04-09T17.md",
      "date": "2026-04-09T17:00:00+08:00",
      "title": {
        "zh": "\u9ece\u5df4\u5ae9\u906d\u88ad\u5f15\u53d1\u5371\u673a\uff1a\u505c\u706b\u534f\u8bae\u906d\u4e25\u91cd\u8fdd\u7ea6\uff0c\u6cb9\u4ef7\u53cd\u5f39",
        "en": "\u9ece\u5df4\u5ae9\u906d\u88ad\u5f15\u53d1\u5371\u673a\uff1a\u505c\u706b\u534f\u8bae\u906d\u4e25\u91cd\u8fdd\u7ea6\uff0c\u6cb9\u4ef7\u53cd\u5f39"
      },
      "tags": [
        ""
      ]
    },
    {
      "id": "2026-04-09T16",
      "file": "2026-04-09T16.md",
      "date": "2026-04-09T16:00:00+08:00",
      "title": {
        "zh": "\u505c\u706b\u9047\u632b\uff1a\u7279\u6717\u666e\u589e\u5175\u5a01\u80c1\u6b66\u529b\uff0c\u9ece\u4ee5\u51b2\u7a81\u9020\u6210\u4e25\u91cd\u5e73\u6c11\u4f24\u4ea1",
        "en": "\u505c\u706b\u9047\u632b\uff1a\u7279\u6717\u666e\u589e\u5175\u5a01\u80c1\u6b66\u529b\uff0c\u9ece\u4ee5\u51b2\u7a81\u9020\u6210\u4e25\u91cd\u5e73\u6c11\u4f24\u4ea1"
      },
      "tags": [
        ""
      ]
    },
    {
      "id": "2026-04-09T12",
      "file": "2026-04-09T12.md",
      "date": "2026-04-09T12:00:00+08:00",
      "title": {
        "zh": "\u505c\u706b\u534f\u8bae\u9762\u4e34\u65b0\u6311\u6218\uff1a\u7279\u6717\u666e\u589e\u5175\u4e2d\u4e1c\uff0c\u8054\u5408\u56fd\u8b66\u544a\u9ece\u5df4\u5ae9\u884c\u52a8\u98ce\u9669",
        "en": "\u505c\u706b\u534f\u8bae\u9762\u4e34\u65b0\u6311\u6218\uff1a\u7279\u6717\u666e\u589e\u5175\u4e2d\u4e1c\uff0c\u8054\u5408\u56fd\u8b66\u544a\u9ece\u5df4\u5ae9\u884c\u52a8\u98ce\u9669"
      },
      "tags": [
        ""
      ]
    },
    {
      "id": "2026-04-09T06",
      "file": "2026-04-09T06.md",
      "date": "2026-04-09T06:00:00+08:00",
      "title": {
        "zh": "\u505c\u706b\u534f\u8bae\u52a8\u6447\uff1a\u4f0a\u6717\u6307\u63a7\u7f8e\u56fd\u8fdd\u53cd\u6846\u67b6\uff0c\u4ee5\u8272\u5217\u6269\u5927\u9ece\u5df4\u5ae9\u6253\u51fb",
        "en": "\u505c\u706b\u534f\u8bae\u52a8\u6447\uff1a\u4f0a\u6717\u6307\u63a7\u7f8e\u56fd\u8fdd\u53cd\u6846\u67b6\uff0c\u4ee5\u8272\u5217\u6269\u5927\u9ece\u5df4\u5ae9\u6253\u51fb"
      },
      "tags": [
        ""
      ]
    },
    {
      "id": "2026-04-09T02",
      "file": "2026-04-09T02.md",
      "date": "2026-04-09T02:00:00+08:00",
      "title": {
        "zh": "\u4f0a\u6717\u56e0\u9ece\u5df4\u5ae9\u88ad\u51fb\u5173\u95ed\u970d\u5c14\u6728\u5179\u6d77\u5ce1",
        "en": "\u4f0a\u6717\u56e0\u9ece\u5df4\u5ae9\u88ad\u51fb\u5173\u95ed\u970d\u5c14\u6728\u5179\u6d77\u5ce1"
      },
      "tags": [
        ""
      ]
    },
    {
      "id": "2026-04-09T00",
      "file": "2026-04-09T00.md",
      "date": "2026-04-09T00:00:00+08:00",
      "title": {
        "zh": "\u7279\u6717\u666e\u79f0\u5c06\u4e0e\u4f0a\u6717\u5408\u4f5c\u5f00\u91c7\u94c0\u6d53\u7f29\u6750\u6599\uff0c\u4ee5\u8272\u5217\u7ee7\u7eed\u8f70\u70b8\u8d1d\u9c81\u7279",
        "en": "\u7279\u6717\u666e\u79f0\u5c06\u4e0e\u4f0a\u6717\u5408\u4f5c\u5f00\u91c7\u94c0\u6d53\u7f29\u6750\u6599\uff0c\u4ee5\u8272\u5217\u7ee7\u7eed\u8f70\u70b8\u8d1d\u9c81\u7279"
      },
      "tags": [
        ""
      ]
    },
    {
      "id": "2026-04-08T23",
      "file": "2026-04-08T23.md",
      "date": "2026-04-08T23:00:00+08:00",
      "title": {
        "zh": "\u505c\u706b\u534f\u8bae\u521d\u6b65\u751f\u6548\uff0c\u4ee5\u8272\u5217\u7ee7\u7eed\u6253\u51fb\u9ece\u5df4\u5ae9\u771f\u4e3b\u515a",
        "en": "\u505c\u706b\u534f\u8bae\u521d\u6b65\u751f\u6548\uff0c\u4ee5\u8272\u5217\u7ee7\u7eed\u6253\u51fb\u9ece\u5df4\u5ae9\u771f\u4e3b\u515a"
      },
      "tags": [
        ""
      ]
    },
    {
      "id": "2026-04-08T21",
      "file": "2026-04-08T21.md",
      "date": "2026-04-08T21:00:00+08:00",
      "title": {
        "zh": "\u505c\u706b\u534f\u8bae\u540e\u7eed\u53d1\u5c55\uff1a\u4f0a\u6717\u603b\u7edf\u5f3a\u786c\u8868\u6001\uff0c\u970d\u5c14\u6728\u5179\u6d77\u5ce1\u901a\u884c\u95ee\u9898\u6301\u7eed",
        "en": "\u505c\u706b\u534f\u8bae\u540e\u7eed\u53d1\u5c55\uff1a\u4f0a\u6717\u603b\u7edf\u5f3a\u786c\u8868\u6001\uff0c\u970d\u5c14\u6728\u5179\u6d77\u5ce1\u901a\u884c\u95ee\u9898\u6301\u7eed"
      },
      "tags": [
        ""
      ]
    },
    {
      "id": "2026-04-08T20",
      "file": "2026-04-08T20.md",
      "date": "2026-04-08T20:00:00+08:00",
      "title": {
        "zh": "\u4f0a\u6717\u62df\u5f81\u6536\u970d\u5c14\u6728\u5179\u6d77\u5ce1\u901a\u884c\u8d39\uff0c\u505c\u706b\u540e\u65b0\u5c40\u52bf\u5c55\u5f00",
        "en": "\u4f0a\u6717\u62df\u5f81\u6536\u970d\u5c14\u6728\u5179\u6d77\u5ce1\u901a\u884c\u8d39\uff0c\u505c\u706b\u540e\u65b0\u5c40\u52bf\u5c55\u5f00"
      },
      "tags": [
        ""
      ]
    },
    {
      "id": "2026-04-08T19",
      "file": "2026-04-08T19.md",
      "date": "2026-04-08T19:00:00+08:00",
      "title": {
        "zh": "\u505c\u706b\u540e\u77f3\u6cb9\u66b4\u8dcc\uff0c\u7f8e\u4f0a\u51b2\u7a81\u6301\u7eed\u5347\u7ea7",
        "en": "\u505c\u706b\u540e\u77f3\u6cb9\u66b4\u8dcc\uff0c\u7f8e\u4f0a\u51b2\u7a81\u6301\u7eed\u5347\u7ea7"
      },
      "tags": [
        ""
      ]
    },
    {
      "id": "2026-04-08T18",
      "file": "2026-04-08T18.md",
      "date": "2026-04-08T18:00:00+08:00",
      "title": {
        "zh": "\u4f0a\u6717\u5ba3\u5e03\u80dc\u5229 \u505c\u706b\u540e talks \u5c06\u5728\u4f0a\u65af\u5170\u5821\u8fdb\u884c",
        "en": "\u4f0a\u6717\u5ba3\u5e03\u80dc\u5229 \u505c\u706b\u540e talks \u5c06\u5728\u4f0a\u65af\u5170\u5821\u8fdb\u884c"
      },
      "tags": [
        ""
      ]
    },
    {
      "id": "2026-04-08T16",
      "file": "2026-04-08T16.md",
      "date": "2026-04-08T16:00:00+08:00",
      "title": {
        "zh": "\u9ece\u4ee5\u8fb9\u5883\u51b2\u7a81\u6301\u7eed \u5e02\u573a\u5f3a\u52bf\u53cd\u5f39",
        "en": "\u9ece\u4ee5\u8fb9\u5883\u51b2\u7a81\u6301\u7eed \u5e02\u573a\u5f3a\u52bf\u53cd\u5f39"
      },
      "tags": [
        ""
      ]
    },
    {
      "id": "2026-04-08T14",
      "file": "2026-04-08T14.md",
      "date": "2026-04-08T14:00:00+08:00",
      "title": {
        "zh": "\u5df4\u6797\u906d\u9047\u7206\u70b8\u88ad\u51fb\uff0c\u505c\u706b\u534f\u8bae\u6392\u9664\u9ece\u5df4\u5ae9",
        "en": "\u5df4\u6797\u906d\u9047\u7206\u70b8\u88ad\u51fb\uff0c\u505c\u706b\u534f\u8bae\u6392\u9664\u9ece\u5df4\u5ae9"
      },
      "tags": [
        ""
      ]
    },
    {
      "id": "2026-04-08T11",
      "file": "2026-04-08T11.md",
      "date": "2026-04-08T11:00:00+08:00",
      "title": {
        "zh": "\u7f8e\u4f0a\u8fbe\u6210\u4e24\u5468\u505c\u706b\u534f\u8bae\uff0c\u4ee5\u8272\u5217\u8868\u793a\u4e0d\u5305\u542b\u5bf9\u771f\u4e3b\u515a\u6218\u6597",
        "en": "\u7f8e\u4f0a\u8fbe\u6210\u4e24\u5468\u505c\u706b\u534f\u8bae\uff0c\u4ee5\u8272\u5217\u8868\u793a\u4e0d\u5305\u542b\u5bf9\u771f\u4e3b\u515a\u6218\u6597"
      },
      "tags": [
        ""
      ]
    },
    {
      "id": "2026-04-08T09",
      "file": "2026-04-08T09.md",
      "date": "2026-04-08T09:00:00+08:00",
      "title": {
        "zh": "\u7b2c\u516d\u6b21\u505c\u706b\u5ef6\u671f\u8c08\u5224\u5f00\u542f\uff0c\u4f0a\u6717\u897f\u90e8\u519b\u4e8b\u51b2\u7a81\u5347\u7ea7",
        "en": "\u7b2c\u516d\u6b21\u505c\u706b\u5ef6\u671f\u8c08\u5224\u5f00\u542f\uff0c\u4f0a\u6717\u897f\u90e8\u519b\u4e8b\u51b2\u7a81\u5347\u7ea7"
      },
      "tags": [
        ""
      ]
    },
    {
      "id": "2026-04-08T07",
      "file": "2026-04-08T07.md",
      "date": "2026-04-08T07:00:00+08:00",
      "title": {
        "zh": "\u7279\u6717\u666e\u5ba3\u5e03\u4e24\u5468\u505c\u706b\u534f\u8bae\uff0c\u907f\u514d\u6587\u660e\u5a01\u80c1\u5b9e\u73b0",
        "en": "\u7279\u6717\u666e\u5ba3\u5e03\u4e24\u5468\u505c\u706b\u534f\u8bae\uff0c\u907f\u514d\u6587\u660e\u5a01\u80c1\u5b9e\u73b0"
      },
      "tags": [
        ""
      ]
    },
    {
      "id": "2026-04-08T05",
      "file": "2026-04-08T05.md",
      "date": "2026-04-08T05:00:00+08:00",
      "title": {
        "zh": "\u7279\u6717\u666e\u5a01\u80c1\u6467\u6bc1\u6587\u660e\u4e0e\u4f0a\u6717\u6269\u5927\u53cd\u5236",
        "en": "\u7279\u6717\u666e\u5a01\u80c1\u6467\u6bc1\u6587\u660e\u4e0e\u4f0a\u6717\u6269\u5927\u53cd\u5236"
      },
      "tags": [
        ""
      ]
    },
    {
      "id": "2026-04-08T04",
      "file": "2026-04-08T04.md",
      "date": "2026-04-08T04:00:00+08:00",
      "title": {
        "zh": "\u7279\u6717\u666e\u518d\u53d1'\u6587\u660e\u6b7b\u4ea1\u5a01\u80c1' \u591a\u56fd\u7d27\u6025\u5e94\u5bf9\u8054\u5408\u56fd\u8868\u51b3\u53d7\u963b",
        "en": "\u7279\u6717\u666e\u518d\u53d1'\u6587\u660e\u6b7b\u4ea1\u5a01\u80c1' \u591a\u56fd\u7d27\u6025\u5e94\u5bf9\u8054\u5408\u56fd\u8868\u51b3\u53d7\u963b"
      },
      "tags": [
        ""
      ]
    },
    {
      "id": "2026-04-08T03:00:00+08:00",
      "file": "2026-04-08T03.md",
      "date": "2026-04-08T03:00:00+08:00",
      "title": {
        "zh": "\u7279\u6717\u666e'\u6587\u660e\u6bc1\u706d'\u5a01\u80c1\u5f15\u7206\u56fd\u9645\u8c34\u8d23 \u4f0a\u6717\u5bfc\u5f39\u7b2c7\u6b21\u88ad\u51fb\u4ee5\u8272\u5217",
        "en": "\u7279\u6717\u666e'\u6587\u660e\u6bc1\u706d'\u5a01\u80c1\u5f15\u7206\u56fd\u9645\u8c34\u8d23 \u4f0a\u6717\u5bfc\u5f39\u7b2c7\u6b21\u88ad\u51fb\u4ee5\u8272\u5217"
      },
      "tags": [
        ""
      ]
    },
    {
      "id": "2026-04-08T02",
      "file": "2026-04-08T02.md",
      "date": "2026-04-08T02:00:00+08:00",
      "title": {
        "zh": "\u7279\u6717\u666e\u5a01\u80c1\u6467\u6bc1\u4f0a\u6717\u80fd\u6e90\u8bbe\u65bd \u4f0a\u6717\u62d2\u7edd\u505c\u706b\u8c08\u5224\u9677\u5165\u50f5\u5c40",
        "en": "\u7279\u6717\u666e\u5a01\u80c1\u6467\u6bc1\u4f0a\u6717\u80fd\u6e90\u8bbe\u65bd \u4f0a\u6717\u62d2\u7edd\u505c\u706b\u8c08\u5224\u9677\u5165\u50f5\u5c40"
      },
      "tags": [
        ""
      ]
    },
    {
      "id": "2026-04-08T00",
      "file": "2026-04-08T00.md",
      "date": "2026-04-08T00:00:00+08:00",
      "title": {
        "zh": "\u7279\u6717\u666e'\u6587\u660e\u6b7b\u4ea1\u8b66\u544a'\u5347\u6e29\uff0c\u7f8e\u4ee5\u518d\u5ea6\u6253\u51fb\u4f0a\u6717\u57fa\u7840\u8bbe\u65bd",
        "en": "\u7279\u6717\u666e'\u6587\u660e\u6b7b\u4ea1\u8b66\u544a'\u5347\u6e29\uff0c\u7f8e\u4ee5\u518d\u5ea6\u6253\u51fb\u4f0a\u6717\u57fa\u7840\u8bbe\u65bd"
      },
      "tags": [
        ""
      ]
    },
    {
      "id": "2026-04-07T23",
      "file": "2026-04-07T23.md",
      "date": "2026-04-07T23:00:00+08:00",
      "title": {
        "zh": "Deadline\u524d\u591c\uff1a\u4ee5\u8272\u5217\u786e\u8ba4\u6253\u51fb8\u5ea7\u6865\u6881\uff0c\u7279\u6717\u666e\u906d\u4e24\u515a\u62a8\u51fb\uff0c\u4f0a\u6717\u5173\u95ed\u5bf9\u7f8e\u5916\u4ea4\u6e20\u9053\uff0c\u82f1\u56fd\u62d2\u7edd\u7f8e\u519b\u4f7f\u7528\u57fa\u5730",
        "en": "Deadline\u524d\u591c\uff1a\u4ee5\u8272\u5217\u786e\u8ba4\u6253\u51fb8\u5ea7\u6865\u6881\uff0c\u7279\u6717\u666e\u906d\u4e24\u515a\u62a8\u51fb\uff0c\u4f0a\u6717\u5173\u95ed\u5bf9\u7f8e\u5916\u4ea4\u6e20\u9053\uff0c\u82f1\u56fd\u62d2\u7edd\u7f8e\u519b\u4f7f\u7528\u57fa\u5730"
      },
      "tags": [
        ""
      ]
    },
    {
      "id": "2026-04-07T22",
      "file": "2026-04-07T22.md",
      "date": "2026-04-07T22:00:00+08:00",
      "title": {
        "zh": "\u54c8\u5c14\u514b\u5c9b\u906d\u591a\u6b21\u6253\u51fb\uff0c\u7279\u6717\u666e\u53d1\u51fa'\u6587\u660e\u6d88\u4ea1'\u5a01\u80c1\uff0c\u4f0a\u6717\u8a93\u8a00\u8de8\u533a\u57df\u62a5\u590d",
        "en": "\u54c8\u5c14\u514b\u5c9b\u906d\u591a\u6b21\u6253\u51fb\uff0c\u7279\u6717\u666e\u53d1\u51fa'\u6587\u660e\u6d88\u4ea1'\u5a01\u80c1\uff0c\u4f0a\u6717\u8a93\u8a00\u8de8\u533a\u57df\u62a5\u590d"
      },
      "tags": [
        ""
      ]
    },
    {
      "id": "2026-04-07T21",
      "file": "2026-04-07T21.md",
      "date": "2026-04-07T21:00:00+08:00",
      "title": {
        "zh": "Deadline\u5012\u8ba1\u65f6\uff1a\u7a7a\u88ad\u4f0a\u6717\u6865\u6881\u706b\u8f66\u7ad9\uff0c\u7279\u6717\u666e\u79f0'\u6574\u4e2a\u6587\u660e\u4eca\u665a\u5c06\u6d88\u4ea1'\uff0c\u7f8e\u519b\u518d\u6b21\u6253\u51fb\u54c8\u5c14\u514b\u5c9b",
        "en": "Deadline\u5012\u8ba1\u65f6\uff1a\u7a7a\u88ad\u4f0a\u6717\u6865\u6881\u706b\u8f66\u7ad9\uff0c\u7279\u6717\u666e\u79f0'\u6574\u4e2a\u6587\u660e\u4eca\u665a\u5c06\u6d88\u4ea1'\uff0c\u7f8e\u519b\u518d\u6b21\u6253\u51fb\u54c8\u5c14\u514b\u5c9b"
      },
      "tags": [
        ""
      ]
    },
    {
      "id": "2026-04-07T19",
      "file": "2026-04-07T19.md",
      "date": "2026-04-07T19:00:00+08:00",
      "title": {
        "zh": "\u7279\u6717\u666e\u8b66\u544a\u671f\u9650\u5230\u4e34\uff1a\u4ee5\u8272\u5217\u8b66\u544a\u4f0a\u6717\u4eba\u505c\u7528\u706b\u8f66\uff0c\u6c99\u7279\u5173\u95ed\u4e0e\u5df4\u6797\u901a\u9053",
        "en": "\u7279\u6717\u666e\u8b66\u544a\u671f\u9650\u5230\u4e34\uff1a\u4ee5\u8272\u5217\u8b66\u544a\u4f0a\u6717\u4eba\u505c\u7528\u706b\u8f66\uff0c\u6c99\u7279\u5173\u95ed\u4e0e\u5df4\u6797\u901a\u9053"
      },
      "tags": [
        "generated"
      ]
    },
    {
      "id": "2026-04-07T18",
      "file": "2026-04-07T18.md",
      "date": "2026-04-07T18:00:00+08:00",
      "title": {
        "zh": "Deadline\u5230\u671f\u524d\u5915\uff1a\u4f0a\u6717\u62d2\u7edd\u4e34\u65f6\u505c\u706b\uff0c\u7279\u6717\u666e\u5a01\u80c14\u5c0f\u65f6\u6467\u6bc1\u57fa\u7840\u8bbe\u65bd",
        "en": "Deadline\u5230\u671f\u524d\u5915\uff1a\u4f0a\u6717\u62d2\u7edd\u4e34\u65f6\u505c\u706b\uff0c\u7279\u6717\u666e\u5a01\u80c14\u5c0f\u65f6\u6467\u6bc1\u57fa\u7840\u8bbe\u65bd"
      },
      "tags": [
        ""
      ]
    }
  ],
  "total_files": 28,
  "generated_at": "2026-04-11T23:10:00+08:00"
}