{
  "updated": "2026-04-07T23:00:00Z",
  "files": [
    {
      "id": "2026-04-07T23",
      "file": "2026-04-07T23.md",
      "date": "2026-04-07T23:00:00Z",
      "title": {
        "zh": "美伊战争：特朗普最后期限逼近，德黑兰拒绝45天停火",
        "en": "Iran War: Trump's Final Deadline Looms, Tehran Rejects 45-Day Ceasefire"
      },
      "tags": ["military", "diplomacy"]
    },
    {
      "id": "2026-04-07T11",
      "file": "2026-04-07T11.md",
      "date": "2026-04-07T11:00:00Z",
      "title": {
        "zh": "特朗普警告期限到临：以色列警告伊朗人停用火车，沙特关闭与巴林通道",
        "en": "Trump's Deadline Looms: Israel Warns Iranians to Avoid Trains, Saudi Closes Link to Bahrain"
      },
      "tags": ["military", "diplomacy", "politics"]
    },
    {
      "id": "2026-04-07T10",
      "file": "2026-04-07T10.md",
      "date": "2026-04-07T10:00:00Z",
      "title": {
        "zh": "Deadline到期前夕：伊朗拒绝临时停火，特朗普威胁4小时摧毁基础设施",
        "en": "Eve of Deadline: Iran Rejects Ceasefire, Trump Threatens to Destroy Infrastructure in 4 Hours"
      },
      "tags": ["military", "diplomacy", "politics"]
    }
  ]
}
